vcd/__init__.py
vcd/common.py
vcd/gtkw.py
vcd/py.typed
vcd/reader.py
vcd/writer.py
pyvcd-0.3.0.dist-info/LICENSE.txt
pyvcd-0.3.0.dist-info/METADATA
pyvcd-0.3.0.dist-info/WHEEL
pyvcd-0.3.0.dist-info/top_level.txt
pyvcd-0.3.0.dist-info/RECORD
